{"id": 0, "curation_reward_curve": "square_root", "reward_balance": "743994.027 STEEM", "name": "post", "last_update": "2018-06-21T17:33:18", "author_reward_curve": "linear", "content_constant": "2000000000000", "percent_content_rewards": 10000, "recent_claims": "472970584378626960", "percent_curation_rewards": 2500}
{"virtual_supply": "279574873.000 STEEM", "sbd_print_rate": 5533, "current_reserve_ratio": 200000000, "last_irreversible_block_num": 23522148, "maximum_block_size": 65536, "pending_rewarded_vesting_shares": "404506925.153452 VESTS", "head_block_id": "0166eb75491b342384adf569b5eb968be920c3b8", "max_virtual_bandwidth": "264241152000000000000", "head_block_number": 23522165, "total_vesting_fund_steem": "192270346.255 STEEM", "current_witness": "roelandp", "total_reward_fund_steem": "0.000 STEEM", "total_reward_shares2": "0", "total_vesting_shares": "390505808595.623203 VESTS", "current_supply": "270229314.139 STEEM", "confidential_supply": "0.000 STEEM", "sbd_interest_rate": 0, "average_block_size": 13334, "participation_count": 128, "confidential_sbd_supply": "0.000 SBD", "recent_slots_filled": "340282366920938463463374607431768211455", "pending_rewarded_vesting_steem": "197508.037 STEEM", "total_pow": 514415, "vote_power_reserve_rate": 10, "num_pow_witnesses": 172, "current_sbd_supply": "15214569.827 SBD", "time": "2018-06-21T17:33:18", "current_aslot": 23589066}

{"id": 0, "name": "post", "last_update": "2018-06-22T16:56:45", "author_reward_curve": "linear", "recent_claims": "473165455410984110", "curation_reward_curve": "square_root", "percent_curation_rewards": 2500, "content_constant": "2000000000000", "percent_content_rewards": 10000, "reward_balance": "744900.977 STEEM"}
{"total_reward_fund_steem": "0.000 STEEM", "num_pow_witnesses": 172, "virtual_supply": "279792519.638 STEEM", "total_vesting_shares": "390547870093.222377 VESTS", "current_witness": "followbtcnews", "vote_power_reserve_rate": 10, "max_virtual_bandwidth": "262735591794278400000", "head_block_id": "01675918f0f7d86679d9dbc4b3407f9e6821e64a", "participation_count": 128, "current_aslot": 23617136, "sbd_interest_rate": 0, "recent_slots_filled": "340282366920938463463374607431768211455", "time": "2018-06-22T16:56:48", "current_supply": "270284841.805 STEEM", "pending_rewarded_vesting_steem": "190333.502 STEEM", "last_irreversible_block_num": 23550216, "current_reserve_ratio": 198860465, "average_block_size": 16238, "sbd_print_rate": 5366, "head_block_number": 23550232, "total_reward_shares2": "0", "maximum_block_size": 65536, "confidential_supply": "0.000 STEEM", "total_vesting_fund_steem": "192300884.844 STEEM", "pending_rewarded_vesting_shares": "389828886.968795 VESTS", "total_pow": 514415, "confidential_sbd_supply": "0.000 SBD", "current_sbd_supply": "15231299.890 SBD"}

{"name": "post", "author_reward_curve": "linear", "percent_content_rewards": 10000, "last_update": "2018-06-23T15:33:21", "content_constant": "2000000000000", "curation_reward_curve": "square_root", "recent_claims": "471794733758840999", "percent_curation_rewards": 2500, "id": 0, "reward_balance": "748183.169 STEEM"}
{"time": "2018-06-23T15:33:24", "head_block_number": 23577362, "maximum_block_size": 65536, "total_pow": 514415, "total_reward_fund_steem": "0.000 STEEM", "vote_power_reserve_rate": 10, "current_witness": "clayop", "total_vesting_shares": "390824866121.001966 VESTS", "participation_count": 128, "confidential_sbd_supply": "0.000 SBD", "current_reserve_ratio": 200000000, "sbd_print_rate": 5033, "last_irreversible_block_num": 23577344, "max_virtual_bandwidth": "264241152000000000000", "num_pow_witnesses": 172, "current_sbd_supply": "15245591.597 SBD", "current_aslot": 23644268, "pending_rewarded_vesting_steem": "185343.934 STEEM", "total_reward_shares2": "0", "average_block_size": 13492, "pending_rewarded_vesting_shares": "379573370.571094 VESTS", "sbd_interest_rate": 0, "current_supply": "270339612.217 STEEM", "virtual_supply": "280118695.986 STEEM", "recent_slots_filled": "340282366920938463463374607431768211455", "total_vesting_fund_steem": "192446781.229 STEEM", "head_block_id": "0167c312d34fc94e50742443b32877f57f94d4f8", "confidential_supply": "0.000 STEEM"}

{"author_reward_curve": "linear", "curation_reward_curve": "square_root", "id": 0, "percent_content_rewards": 10000, "recent_claims": "471605813043569361", "name": "post", "content_constant": "2000000000000", "reward_balance": "749744.481 STEEM", "percent_curation_rewards": 2500, "last_update": "2018-06-24T17:43:36"}
{"current_reserve_ratio": 200000000, "current_supply": "270404862.254 STEEM", "current_sbd_supply": "15258433.667 SBD", "num_pow_witnesses": 172, "confidential_supply": "0.000 STEEM", "confidential_sbd_supply": "0.000 SBD", "sbd_print_rate": 3433, "total_reward_shares2": "0", "head_block_id": "01683db6754b90bcd1ec7f991062ce32a4383bf3", "pending_rewarded_vesting_steem": "175528.181 STEEM", "last_irreversible_block_num": 23608738, "head_block_number": 23608758, "time": "2018-06-24T17:43:36", "total_reward_fund_steem": "0.000 STEEM", "max_virtual_bandwidth": "264241152000000000000", "sbd_interest_rate": 0, "maximum_block_size": 65536, "vote_power_reserve_rate": 10, "pending_rewarded_vesting_shares": "359458427.815800 VESTS", "average_block_size": 13810, "current_aslot": 23675672, "virtual_supply": "281591397.200 STEEM", "current_witness": "aggroed", "participation_count": 128, "recent_slots_filled": "340282366920938463463374607431768211455", "total_pow": 514415, "total_vesting_fund_steem": "192509538.006 STEEM", "total_vesting_shares": "390929928076.640579 VESTS"}

{"percent_curation_rewards": 2500, "last_update": "2018-06-25T16:58:15", "author_reward_curve": "linear", "curation_reward_curve": "square_root", "id": 0, "reward_balance": "750047.346 STEEM", "name": "post", "percent_content_rewards": 10000, "recent_claims": "472162286547538941", "content_constant": "2000000000005"}
{"participation_count": 128, "average_block_size": 15563, "total_vesting_fund_steem": "192600056.042 STEEM", "total_pow": 514415, "sbd_interest_rate": 0, "vote_power_reserve_rate": 10, "last_irreversible_block_num": 23636624, "total_reward_shares2": "0", "current_aslot": 23703565, "current_sbd_supply": "15266726.336 SBD", "confidential_sbd_supply": "0.000 SBD", "time": "2018-06-25T16:58:15", "pending_rewarded_vesting_steem": "178072.132 STEEM", "current_witness": "followbtcnews", "pending_rewarded_vesting_shares": "364621836.140674 VESTS", "confidential_supply": "0.000 STEEM", "current_supply": "270464630.480 STEEM", "virtual_supply": "281900380.544 STEEM", "head_block_id": "0168aaa806a205fd47784b32be9d5b73f9bc92db", "sbd_print_rate": 3166, "maximum_block_size": 65536, "current_reserve_ratio": 200000000, "total_vesting_shares": "391093635053.819807 VESTS", "head_block_number": 23636648, "num_pow_witnesses": 172, "recent_slots_filled": "340282366920938463463374607431768211455", "max_virtual_bandwidth": "264241152000000000000", "total_reward_fund_steem": "0.000 STEEM"}

{"percent_curation_rewards": 2500, "reward_balance": "748735.843 STEEM", "id": 0, "percent_content_rewards": 10000, "name": "post", "author_reward_curve": "linear", "curation_reward_curve": "square_root", "recent_claims": "473831450006559123", "last_update": "2018-06-26T17:17:57", "content_constant": "2000000000000"}
{"current_witness": "jesta", "current_supply": "270527262.313 STEEM", "last_irreversible_block_num": 23665811, "pending_rewarded_vesting_steem": "178161.114 STEEM", "confidential_sbd_supply": "0.000 SBD", "vote_power_reserve_rate": 10, "max_virtual_bandwidth": "264241152000000000000", "total_vesting_shares": "391275521174.315342 VESTS", "participation_count": 128, "sbd_print_rate": 3100, "num_pow_witnesses": 172, "virtual_supply": "282021036.447 STEEM", "maximum_block_size": 65536, "time": "2018-06-26T17:17:57", "pending_rewarded_vesting_shares": "364799122.309520 VESTS", "current_sbd_supply": "15275225.825 SBD", "confidential_supply": "0.000 STEEM", "head_block_id": "01691ca75169117221f768c995796d607a070fff", "recent_slots_filled": "340282366920938463463374607431768211455", "average_block_size": 14452, "current_aslot": 23732759, "head_block_number": 23665831, "total_pow": 514415, "total_reward_shares2": "0", "current_reserve_ratio": 200000000, "sbd_interest_rate": 0, "total_vesting_fund_steem": "192699989.980 STEEM", "total_reward_fund_steem": "0.000 STEEM"}

{"reward_balance": "748171.632 STEEM", "name": "post", "id": 0, "last_update": "2018-06-28T16:44:39", "curation_reward_curve": "square_root", "author_reward_curve": "linear", "percent_curation_rewards": 2500, "content_constant": "2000000000000", "recent_claims": "475953999325866277", "percent_content_rewards": 10000}
{"current_witness": "curie", "sbd_interest_rate": 0, "confidential_supply": "0.000 STEEM", "last_irreversible_block_num": 23722741, "total_pow": 514415, "total_vesting_fund_steem": "192508436.379 STEEM", "head_block_id": "0169fb0acf1486c85b450911f6f71346a78a7c7b", "time": "2018-06-28T16:44:39", "maximum_block_size": 65536, "total_reward_shares2": "0", "num_pow_witnesses": 172, "total_vesting_shares": "390845484124.738702 VESTS", "total_reward_fund_steem": "0.000 STEEM", "recent_slots_filled": "340282366920938463463374607431768211455", "head_block_number": 23722762, "pending_rewarded_vesting_steem": "180545.946 STEEM", "current_sbd_supply": "15289514.176 SBD", "average_block_size": 13733, "participation_count": 128, "sbd_print_rate": 2633, "virtual_supply": "282568251.628 STEEM", "vote_power_reserve_rate": 10, "confidential_sbd_supply": "0.000 SBD", "current_aslot": 23789693, "max_virtual_bandwidth": "264241152000000000000", "current_supply": "270651249.153 STEEM", "pending_rewarded_vesting_shares": "369634378.236877 VESTS", "current_reserve_ratio": 200000000}

